torch_template/__init__.py
torch_template/__main__.py
torch_template/version.py
torch_template/dataloader/__init__.py
torch_template/dataloader/image_folder.py
torch_template/dataloader/transforms.py
torch_template/dataloader/tta.py
torch_template/loss/__init__.py
torch_template/loss/cls_loss.py
torch_template/loss/content_loss.py
torch_template/loss/seg_loss.py
torch_template/model_zoo/AttGan.py
torch_template/model_zoo/FFA.py
torch_template/model_zoo/__init__.py
torch_template/model_zoo/blocks.py
torch_template/model_zoo/dense.py
torch_template/model_zoo/discriminator.py
torch_template/model_zoo/linknet.py
torch_template/model_zoo/pix2pix.py
torch_template/model_zoo/transform_net.py
torch_template/model_zoo/unet.py
torch_template/network/__init__.py
torch_template/network/base_model.py
torch_template/network/metrics.py
torch_template/network/norm.py
torch_template/network/weights_init.py
torch_template/templates/README.py
torch_template/templates/__init__.py
torch_template/templates/clear.py
torch_template/templates/eval.py
torch_template/templates/test.py
torch_template/templates/train.py
torch_template/templates/dataloader/__init__.py
torch_template/templates/dataloader/dataset.py
torch_template/templates/network/Model.py
torch_template/templates/network/__init__.py
torch_template/templates/options/__init__.py
torch_template/templates/options/options.py
torch_template/utils/__init__.py
torch_template/utils/misc_utils(duplicated).py
torch_template/utils/torch_utils.py
torch_template-0.0.4.dist-info/LICENSE
torch_template-0.0.4.dist-info/METADATA
torch_template-0.0.4.dist-info/WHEEL
torch_template-0.0.4.dist-info/entry_points.txt
torch_template-0.0.4.dist-info/top_level.txt
torch_template-0.0.4.dist-info/RECORD
