Metadata-Version: 2.1
Name: torch-template
Version: 0.0.4
Summary: Torch_Template - A PyTorch template with commonly used models and tools
Home-page: https://github.com/misads/torch_template
Author: Haoyu Xu
Author-email: xuhaoyu@tju.edu.cn
License: MIT
Platform: UNKNOWN
Classifier: Development Status :: 3 - Alpha
Classifier: Programming Language :: Python :: 3
Classifier: License :: OSI Approved :: MIT License
Classifier: Operating System :: OS Independent
Requires-Python: >=3.5
Requires-Dist: torch
Requires-Dist: numpy
Requires-Dist: torchvision
Requires-Dist: tensorboardX
Requires-Dist: utils-misc (>=0.0.3)
